ultralink/__init__.py
UltraLink-0.1.1.dist-info/METADATA
UltraLink-0.1.1.dist-info/WHEEL
UltraLink-0.1.1.dist-info/top_level.txt
UltraLink-0.1.1.dist-info/RECORD
