Metadata-Version: 2.1
Name: UltraLink
Version: 0.1.1
Summary: A container for my python modules.
Author: Noah Wilhoite
Author-email: notnoah349@gmail.com
Requires-Dist: requests
